odoo/addons/auth_signup_verify_email/README.rst
odoo/addons/auth_signup_verify_email/__init__.py
odoo/addons/auth_signup_verify_email/__manifest__.py
odoo/addons/auth_signup_verify_email/controllers/__init__.py
odoo/addons/auth_signup_verify_email/controllers/main.py
odoo/addons/auth_signup_verify_email/i18n/auth_signup_verify_email.pot
odoo/addons/auth_signup_verify_email/i18n/da.po
odoo/addons/auth_signup_verify_email/i18n/de.po
odoo/addons/auth_signup_verify_email/i18n/es.po
odoo/addons/auth_signup_verify_email/i18n/fr.po
odoo/addons/auth_signup_verify_email/i18n/hr.po
odoo/addons/auth_signup_verify_email/i18n/hr_HR.po
odoo/addons/auth_signup_verify_email/i18n/it.po
odoo/addons/auth_signup_verify_email/i18n/pt_BR.po
odoo/addons/auth_signup_verify_email/i18n/ro.po
odoo/addons/auth_signup_verify_email/i18n/sl.po
odoo/addons/auth_signup_verify_email/i18n/tr.po
odoo/addons/auth_signup_verify_email/readme/CONFIGURE.rst
odoo/addons/auth_signup_verify_email/readme/CONTRIBUTORS.rst
odoo/addons/auth_signup_verify_email/readme/DESCRIPTION.rst
odoo/addons/auth_signup_verify_email/readme/INSTALL.rst
odoo/addons/auth_signup_verify_email/readme/USAGE.rst
odoo/addons/auth_signup_verify_email/static/description/icon.png
odoo/addons/auth_signup_verify_email/static/description/icon.svg
odoo/addons/auth_signup_verify_email/static/description/index.html
odoo/addons/auth_signup_verify_email/tests/__init__.py
odoo/addons/auth_signup_verify_email/tests/test_verify_email.py
odoo/addons/auth_signup_verify_email/views/signup.xml
odoo12_addon_auth_signup_verify_email-12.0.1.0.3.dist-info/METADATA
odoo12_addon_auth_signup_verify_email-12.0.1.0.3.dist-info/WHEEL
odoo12_addon_auth_signup_verify_email-12.0.1.0.3.dist-info/top_level.txt
odoo12_addon_auth_signup_verify_email-12.0.1.0.3.dist-info/RECORD
