Metadata-Version: 2.1
Name: odoo12-addon-auth-signup-verify-email
Version: 12.0.1.0.3
Summary: Force uninvited users to use a good email for signup
Home-page: https://github.com/OCA/server-auth
Author: Antiun Ingeniería S.L., Tecnativa, Odoo Community Association (OCA)
Author-email: support@odoo-community.org
License: AGPL-3
Platform: UNKNOWN
Classifier: Programming Language :: Python
Classifier: Framework :: Odoo
Classifier: Framework :: Odoo :: 12.0
Classifier: License :: OSI Approved :: GNU Affero General Public License v3
Requires-Python: >=3.5
Requires-Dist: email-validator
Requires-Dist: lxml
Requires-Dist: odoo (<12.1dev,>=12.0a)
